{
  "event": "HECTOR2024",
  "hector": [
    {
      "points": "174.5",
      "diff": "",
      "team": "Juuso Pihamaa + Toni Marttila",
      "through": ""
    },
    {
      "points": "172.3",
      "diff": "+2.2",
      "team": "Miso Korkiakoski + Janne Valtakari",
      "through": "+2.2"
    },
    {
      "points": "172.2",
      "diff": "+2.3",
      "team": "Olli Varis + Jarkko Kailanto",
      "through": "+2.3"
    },
    {
      "points": "172.0",
      "diff": "+2.5",
      "team": "Ofri Porat + Lasse Koskela",
      "through": "+2.5"
    },
    {
      "points": "171.3",
      "diff": "+3.2",
      "team": "Ossi Laukkanen + Lassi Koto",
      "through": "+3.2"
    },
    {
      "points": "170.0",
      "diff": "+4.5",
      "team": "Tommy Gulin + Timo Lukumaa",
      "through": "+4.5"
    },
    {
      "points": "169.7",
      "diff": "+4.8",
      "team": "Pekka Saijonmaa + Pasi Halmetoja",
      "through": "+4.8"
    },
    {
      "points": "167.7",
      "diff": "+6.8",
      "team": "Jussi Allonen + Olli Andersson",
      "through": "+6.8"
    },
    {
      "points": "167.5",
      "diff": "+7",
      "team": "Simo Liukkonen + Mikko Oesch",
      "through": "+7"
    },
    {
      "points": "163.7",
      "diff": "+10.8",
      "team": "Sami Heikkinen + Harri Vainio",
      "through": "+10.8"
    },
    {
      "points": "161.8",
      "diff": "+12.7",
      "team": "Martin Svedholm + Marcus Mattila",
      "through": "+12.7"
    },
    {
      "points": "161.7",
      "diff": "+12.8",
      "team": "Eero Halmetoja + Lauri Paatela",
      "through": "+12.8"
    }
  ],
  "victor": [
    {
      "player": "Eero Halmetoja",
      "points": "96.0",
      "diff": "",
      "through": "3/4"
    },
    {
      "player": "Jussi Allonen",
      "points": "89.0",
      "diff": "-7.0",
      "through": "3/4"
    },
    {
      "player": "Juuso Pihamaa",
      "points": "87.0",
      "diff": "-9.0",
      "through": "3/4"
    },
    {
      "player": "Olli Varis",
      "points": "81.0",
      "diff": "-15.0",
      "through": "3/4"
    },
    {
      "player": "Ofri Porat",
      "points": "80.0",
      "diff": "-16.0",
      "through": "3/4"
    },
    {
      "player": "Martin Svedholm",
      "points": "75.0",
      "diff": "-21.0",
      "through": "3/4"
    },
    {
      "player": "Sami Heikkinen",
      "points": "74.0",
      "diff": "-22.0",
      "through": "3/4"
    },
    {
      "player": "Ossi Laukkanen",
      "points": "73.0",
      "diff": "-23.0",
      "through": "3/4"
    },
    {
      "player": "Tommy Gulin",
      "points": "73.0",
      "diff": "-23.0",
      "through": "3/4"
    },
    {
      "player": "Lassi Koto",
      "points": "72.0",
      "diff": "-24.0",
      "through": "3/4"
    },
    {
      "player": "Pasi Halmetoja",
      "points": "71.0",
      "diff": "-25.0",
      "through": "3/4"
    },
    {
      "player": "Simo Liukkonen",
      "points": "65.0",
      "diff": "-31.0",
      "through": "3/4"
    },
    {
      "player": "Pekka Saijonmaa",
      "points": "64.0",
      "diff": "-32.0",
      "through": "3/4"
    },
    {
      "player": "Lauri Paatela",
      "points": "63.0",
      "diff": "-33.0",
      "through": "2/4"
    },
    {
      "player": "Miso Korkiakoski",
      "points": "62.0",
      "diff": "-34.0",
      "through": "2/4"
    },
    {
      "player": "Marcus Mattila",
      "points": "61.0",
      "diff": "-35.0",
      "through": "2/4"
    },
    {
      "player": "Mikko Oesch",
      "points": "60.0",
      "diff": "-36.0",
      "through": "2/4"
    },
    {
      "player": "Harri Vainio",
      "points": "59.0",
      "diff": "-37.0",
      "through": "2/4"
    },
    {
      "player": "Lasse Koskela",
      "points": "56.0",
      "diff": "-40.0",
      "through": "2/4"
    },
    {
      "player": "Janne Valtakari",
      "points": "54.0",
      "diff": "-42.0",
      "through": "2/4"
    },
    {
      "player": "Timo Lukumaa",
      "points": "48.0",
      "diff": "-48.0",
      "through": "2/4"
    },
    {
      "player": "Olli Andersson",
      "points": "47.0",
      "diff": "-49.0",
      "through": "2/4"
    },
    {
      "player": "Toni Marttila",
      "points": "47.0",
      "diff": "-49.0",
      "through": "2/4"
    },
    {
      "player": "Jarkko Kailanto",
      "points": "34.0",
      "diff": "-62.0",
      "through": "2/4"
    }
  ],
  "updatedAt": "2024-09-06T06:53:17.749Z"
}